<?xml version="1.0" encoding="utf-8"?>
<Defs>
  <ThingDef ParentName="RockBase">
    <defName>MTB_MineableThorium</defName>
    <label>Thorium Formation</label>
    <description>Rare formation of Thorium.</description>
    <graphicData>
      <texPath>Things/Building/Linked/RockFlecked_Atlas</texPath>
      <graphicClass>Graphic_Single</graphicClass>
      <shaderType>CutoutComplex</shaderType>
      <colorTwo>(74,96,64)</colorTwo>
      <color>(70,70,70)</color>
    </graphicData>
    <statBases>
      <Beauty>-1</Beauty>
      <MaxHitPoints>2000</MaxHitPoints>
    </statBases>
    <building>
      <isResourceRock>true</isResourceRock>
      <mineableThing>MTB_Thorium</mineableThing>
      <mineableYield>45</mineableYield>
      <mineableScatterCommonality>0.75</mineableScatterCommonality>
      <mineableScatterLumpSizeRange>
        <min>1</min>
        <max>60</max>
      </mineableScatterLumpSizeRange>
    </building>
  </ThingDef>
</Defs>